biclustlib/__init__.py
biclustlib/io.py
biclustlib/models.py
biclustlib/algorithms/__init__.py
biclustlib/algorithms/_base.py
biclustlib/algorithms/bcca.py
biclustlib/algorithms/bibit.py
biclustlib/algorithms/cca.py
biclustlib/algorithms/las.py
biclustlib/algorithms/plaid.py
biclustlib/algorithms/xmotifs.py
biclustlib/algorithms/wrappers/__init__.py
biclustlib/algorithms/wrappers/_base.py
biclustlib/algorithms/wrappers/_util.py
biclustlib/algorithms/wrappers/bbc.py
biclustlib/algorithms/wrappers/bimax.py
biclustlib/algorithms/wrappers/fabia.py
biclustlib/algorithms/wrappers/isa2.py
biclustlib/algorithms/wrappers/opsm.py
biclustlib/algorithms/wrappers/qubic.py
biclustlib/algorithms/wrappers/rbimax.py
biclustlib/algorithms/wrappers/rcca.py
biclustlib/algorithms/wrappers/rinclose.py
biclustlib/algorithms/wrappers/rplaid.py
biclustlib/algorithms/wrappers/spectral.py
biclustlib/algorithms/wrappers/xmotifs.py
biclustlib/algorithms/wrappers/bin/bbc/BBC
biclustlib/algorithms/wrappers/bin/bbc/LICENSE
biclustlib/algorithms/wrappers/bin/bimax/BiMax.tar.gz
biclustlib/algorithms/wrappers/bin/bimax/bimax
biclustlib/algorithms/wrappers/bin/qubic/qubic
biclustlib/algorithms/wrappers/bin/rinclose/RInClose
biclustlib/algorithms/wrappers/jar/opsm/LICENSE
biclustlib/algorithms/wrappers/jar/opsm/OPSM.jar
biclustlib/benchmark/__init__.py
biclustlib/benchmark/gene_expression.py
biclustlib/benchmark/data/__init__.py
biclustlib/benchmark/data/load.py
biclustlib/benchmark/data/prelic.csv
biclustlib/benchmark/data/tavazoie.csv
biclustlib/benchmark/data/jaskowiak/01_alpha_factor.csv
biclustlib/benchmark/data/jaskowiak/02_cdc_15.csv
biclustlib/benchmark/data/jaskowiak/03_cdc_28.csv
biclustlib/benchmark/data/jaskowiak/04_elutriation.csv
biclustlib/benchmark/data/jaskowiak/05_1mM_menadione.csv
biclustlib/benchmark/data/jaskowiak/06_1M_sorbitol.csv
biclustlib/benchmark/data/jaskowiak/07_15mM_diamide.csv
biclustlib/benchmark/data/jaskowiak/08_25mM_DTT.csv
biclustlib-0.0.13.dist-info/LICENSE
biclustlib-0.0.13.dist-info/METADATA
biclustlib-0.0.13.dist-info/WHEEL
biclustlib-0.0.13.dist-info/top_level.txt
biclustlib-0.0.13.dist-info/RECORD
