Metadata-Version: 2.1
Name: biclustlib
Version: 0.0.13
Summary: A biclustering library with datasets, evaluation measures and a benchmarking framework
Home-page: https://github.com/nikitasigal/biclustlib
Author: Nikita Sigal
Author-email: parallax.nikitasigal@gmail.com
Project-URL: Bug Tracker, https://github.com/nikitasigal/biclustlib/issues
Classifier: Programming Language :: Python :: 3
Classifier: License :: OSI Approved :: GNU General Public License v3 (GPLv3)
Requires-Python: >=3.8
License-File: LICENSE
Requires-Dist: numpy
Requires-Dist: pandas
Requires-Dist: aiohttp
Requires-Dist: matplotlib
Requires-Dist: goatools
Requires-Dist: bottleneck
Requires-Dist: scikit-learn
Requires-Dist: scipy
Requires-Dist: rpy2
Requires-Dist: munkres
